{
  "event_id": "019d4ca3-c81a-73b0-b0ac-673f057114d8",
  "occurred_at": "2026-04-02T05:21:35.252658Z",
  "type": "idx.knot_head",
  "data": {
    "blocked_from_state": null,
    "deferred_from_state": null,
    "gate": {
      "owner_kind": "agent"
    },
    "invariants": [],
    "knot_id": "knots-c8f4",
    "profile_id": "autopilot",
    "state": "ready_for_plan_review",
    "terminal": false,
    "title": "Add per-step expected-output declarations to Loom bundle/runtime",
    "type": "work",
    "updated_at": "2026-04-02T05:21:35.252658Z",
    "workflow_id": "compatibility"
  }
}
