{
  "event_id": "019d4d83-816f-7201-9f68-d1bf8d16f7bf",
  "occurred_at": "2026-04-02T09:25:57.231267Z",
  "type": "idx.knot_head",
  "data": {
    "blocked_from_state": null,
    "deferred_from_state": null,
    "gate": {
      "owner_kind": "agent"
    },
    "invariants": [],
    "knot_id": "knots-c9da",
    "profile_id": "autopilot",
    "state": "lease_ready",
    "terminal": false,
    "title": "Lease: foolery:terminal_manager_take:term-1775120706174-aaj4iz",
    "type": "lease",
    "updated_at": "2026-04-02T09:25:57.231267Z",
    "workflow_id": "compatibility"
  }
}
