{
  "event_id": "019d4ce0-618a-7c21-bfbc-3b9883d78149",
  "occurred_at": "2026-04-02T06:27:46.698082Z",
  "type": "idx.knot_head",
  "data": {
    "blocked_from_state": null,
    "deferred_from_state": null,
    "gate": {
      "owner_kind": "agent"
    },
    "invariants": [],
    "knot_id": "knots-0d93",
    "profile_id": "autopilot",
    "state": "implementation",
    "terminal": false,
    "title": "Update prompt rendering to consume resolved per-step output metadata",
    "type": "work",
    "updated_at": "2026-04-02T06:27:46.698082Z",
    "workflow_id": "compatibility"
  },
  "precondition": {
    "profile_etag": "019d4ce0-2be1-7b81-b892-20b84e3675b1"
  }
}
