{
  "event_id": "019d4dff-d9a2-7f50-8689-ca12433832d7",
  "occurred_at": "2026-04-02T11:41:46.27456Z",
  "type": "idx.knot_head",
  "data": {
    "blocked_from_state": null,
    "deferred_from_state": null,
    "gate": {
      "owner_kind": "agent"
    },
    "invariants": [],
    "knot_id": "knots-3ecc",
    "profile_id": "autopilot",
    "state": "shipped",
    "terminal": true,
    "title": "Unify Knots workflow runtime on Loom",
    "type": "work",
    "updated_at": "2026-04-02T11:41:46.27456Z",
    "workflow_id": "compatibility"
  }
}
