{
  "event_id": "019d67f0-de37-7111-8a72-7fd9982a4776",
  "occurred_at": "2026-04-07T12:35:32.023845Z",
  "type": "idx.knot_head",
  "data": {
    "blocked_from_state": null,
    "deferred_from_state": null,
    "gate": {
      "owner_kind": "agent"
    },
    "invariants": [],
    "knot_id": "knots-c8d8",
    "next_step_metadata": {
      "action_kind": "produce",
      "action_state": "lease_active"
    },
    "profile_id": "autopilot",
    "state": "lease_ready",
    "step_metadata": {
      "action_kind": "produce",
      "action_state": "lease_active"
    },
    "terminal": false,
    "title": "Lease: foolery:terminal_manager_take:term-1775558265675-vpto6y",
    "type": "lease",
    "updated_at": "2026-04-07T12:35:32.023845Z",
    "workflow_id": "compatibility"
  }
}
