{
  "event_id": "019d0607-9dc1-75d0-8e38-3918443c550d",
  "occurred_at": "2026-03-19T12:17:35.681262Z",
  "knot_id": "knots-1cbe",
  "type": "knot.note_added",
  "data": {
    "agentname": "unknown",
    "content": "Extended CLI path coverage to the live-compatible init argument contract discovered during real command verification.",
    "datetime": "2026-03-19T12:17:35.681262Z",
    "entry_id": "019d0607-9dc1-75d0-8e38-390f0d9ffc6d",
    "model": "unknown",
    "username": "unknown",
    "version": "unknown"
  }
}
