{
  "event_id": "019d49d9-fc67-7692-97d4-592824f15a47",
  "occurred_at": "2026-04-01T16:21:55.943737Z",
  "type": "idx.knot_head",
  "data": {
    "blocked_from_state": null,
    "deferred_from_state": null,
    "gate": {
      "owner_kind": "agent"
    },
    "invariants": [],
    "knot_id": "knots-5f86",
    "profile_id": "autopilot",
    "state": "lease_terminated",
    "terminal": true,
    "title": "Lease: foolery:terminal_manager_take:term-1775056925898-dc56bv",
    "type": "lease",
    "updated_at": "2026-04-01T16:21:55.943737Z",
    "workflow_id": "compatibility"
  }
}
