{
  "event_id": "019d4a49-5844-7972-a761-9d0f6ecd4cbc",
  "occurred_at": "2026-04-01T18:23:33.956863Z",
  "type": "idx.knot_head",
  "data": {
    "blocked_from_state": null,
    "deferred_from_state": null,
    "gate": {
      "owner_kind": "agent"
    },
    "invariants": [],
    "knot_id": "knots-be65",
    "profile_id": "autopilot",
    "state": "lease_active",
    "terminal": false,
    "title": "Lease: foolery:terminal_manager_take:term-1775065506345-2bd1fr",
    "type": "lease",
    "updated_at": "2026-04-01T18:23:33.956863Z",
    "workflow_id": "compatibility"
  }
}
