{
  "event_id": "019d4a31-8fe6-7d30-8d8c-e52ac543a30b",
  "occurred_at": "2026-04-01T17:57:35.328383Z",
  "type": "idx.knot_head",
  "data": {
    "blocked_from_state": null,
    "deferred_from_state": null,
    "gate": {
      "owner_kind": "agent"
    },
    "invariants": [],
    "knot_id": "knots-5464",
    "profile_id": "autopilot",
    "state": "planning",
    "terminal": false,
    "title": "Model Per-Step Output Targets in Loom Workflows",
    "type": "work",
    "updated_at": "2026-04-01T17:57:35.328383Z",
    "workflow_id": "compatibility"
  }
}
