{
  "event_id": "019d6d31-3537-7483-96bb-84f0af89874c",
  "occurred_at": "2026-04-08T13:03:54.679539Z",
  "type": "idx.knot_head",
  "data": {
    "blocked_from_state": null,
    "deferred_from_state": null,
    "gate": {
      "owner_kind": "agent"
    },
    "invariants": [],
    "knot_id": "knots-7884",
    "next_step_metadata": {
      "action_kind": "gate",
      "action_state": "implementation_review",
      "output": {
        "artifact_type": "remote_main"
      },
      "owner": {
        "agent_model": null,
        "agent_name": null,
        "agent_version": null,
        "kind": "agent"
      }
    },
    "profile_id": "autopilot",
    "state": "implementation",
    "step_metadata": {
      "action_kind": "produce",
      "action_state": "implementation",
      "output": {
        "artifact_type": "remote_main"
      },
      "owner": {
        "agent_model": null,
        "agent_name": null,
        "agent_version": null,
        "kind": "agent"
      }
    },
    "terminal": false,
    "title": "Rename builtin workflow id to work_sdlc",
    "type": "work",
    "updated_at": "2026-04-08T13:03:54.679539Z",
    "workflow_id": "compatibility"
  },
  "precondition": {
    "profile_etag": "019d6d31-2e53-71f0-838d-ce35995c0b8c"
  }
}
