{
  "event_id": "019cffc7-3d16-71e2-89de-d3e04898557c",
  "occurred_at": "2026-03-18T07:09:33.304018Z",
  "type": "idx.knot_head",
  "data": {
    "deferred_from_state": null,
    "gate": {
      "owner_kind": "agent"
    },
    "invariants": [],
    "knot_id": "knots-0fc6",
    "profile_id": "autopilot",
    "state": "implementation",
    "terminal": false,
    "title": "kno doctor: identify parents whose children are all in terminal state and resolve them",
    "type": "work",
    "updated_at": "2026-03-18T07:09:33.304018Z"
  }
}
