{
  "event_id": "019d1979-2d02-7840-9373-49b817a6fcec",
  "occurred_at": "2026-03-23T06:54:25.026837Z",
  "type": "idx.knot_head",
  "data": {
    "deferred_from_state": null,
    "gate": {
      "owner_kind": "agent"
    },
    "invariants": [],
    "knot_id": "knots-4730",
    "profile_id": "autopilot_with_pr",
    "state": "lease_active",
    "terminal": false,
    "title": "Lease: foolery:terminal_manager_take:term-1774247803145-2b063q",
    "type": "lease",
    "updated_at": "2026-03-23T06:54:25.026837Z",
    "workflow_id": "compatibility"
  }
}
