{
  "event_id": "019d5209-9d06-7752-8dd2-781011719d53",
  "occurred_at": "2026-04-03T06:30:54.982001Z",
  "type": "idx.knot_head",
  "data": {
    "blocked_from_state": null,
    "deferred_from_state": null,
    "gate": {
      "owner_kind": "agent"
    },
    "invariants": [],
    "knot_id": "knots-5119",
    "profile_id": "autopilot",
    "state": "lease_active",
    "step_metadata": {
      "action_kind": "produce",
      "action_state": "lease_active"
    },
    "terminal": false,
    "title": "Lease: foolery:terminal_manager_take:term-1775194337598-rcsorh",
    "type": "lease",
    "updated_at": "2026-04-03T06:30:54.982001Z",
    "workflow_id": "compatibility"
  }
}
