{
  "event_id": "019d51e0-ec56-78a2-8079-86356b9406cf",
  "occurred_at": "2026-04-03T05:46:28.310025Z",
  "type": "idx.knot_head",
  "data": {
    "blocked_from_state": null,
    "deferred_from_state": null,
    "gate": {
      "owner_kind": "agent"
    },
    "invariants": [],
    "knot_id": "knots-8eca",
    "profile_id": "autopilot",
    "state": "lease_terminated",
    "terminal": true,
    "title": "Lease: foolery:terminal_manager_take:term-1775194301419-i4yjwp",
    "type": "lease",
    "updated_at": "2026-04-03T05:46:28.310025Z",
    "workflow_id": "compatibility"
  }
}
